django_reverse_relationship-0.1.0.dist-info/licenses/LICENSE
reverse_relationship/__init__.py
reverse_relationship/admin.py
reverse_relationship/apps.py
reverse_relationship/forms.py
django_reverse_relationship-0.1.0.dist-info/METADATA
django_reverse_relationship-0.1.0.dist-info/WHEEL
django_reverse_relationship-0.1.0.dist-info/top_level.txt
django_reverse_relationship-0.1.0.dist-info/RECORD
