Metadata-Version: 2.4
Name: django-reverse-relationship
Version: 0.1.0
Summary: A model form factory and admin class that includes reverse related fields
Author-email: Brian Gaudino <bgaudino@gmail.com>
License: BSD-3-Clause
Project-URL: homepage, https://github.com/bgaudino/django-reverse-relationship
Project-URL: repository, https://github.com/bgaudino/django-reverse-relationship
Classifier: Development Status :: 1 - Planning
Classifier: Environment :: Web Environment
Classifier: Framework :: Django
Classifier: Framework :: Django :: 4.2
Classifier: Framework :: Django :: 5.0
Classifier: Framework :: Django :: 5.1
Classifier: Framework :: Django :: 5.2
Classifier: Intended Audience :: Developers
Classifier: Natural Language :: English
Classifier: Programming Language :: Python
Classifier: Programming Language :: Python :: 3
Classifier: Programming Language :: Python :: 3.8
Classifier: Programming Language :: Python :: 3.9
Classifier: Programming Language :: Python :: 3.10
Classifier: Programming Language :: Python :: 3.11
Classifier: Programming Language :: Python :: 3.12
Classifier: Programming Language :: Python :: 3.13
Requires-Python: >=3.8
License-File: LICENSE
Requires-Dist: Django>=4.2
Provides-Extra: dev
Requires-Dist: black>=24.8.0; extra == "dev"
Requires-Dist: coverage>=7.6.1; extra == "dev"
Requires-Dist: pytest-django>=4.9.0; extra == "dev"
Requires-Dist: pytest>=8.3.4; extra == "dev"
Requires-Dist: tox>=4.24.1; extra == "dev"
Dynamic: license-file
